AsyncPywhatKit/src/__init__.py
AsyncPywhatKit/src/ascii_art.py
AsyncPywhatKit/src/handwriting.py
AsyncPywhatKit/src/mail.py
AsyncPywhatKit/src/misc.py
AsyncPywhatKit/src/remotekit.py
AsyncPywhatKit/src/sc.py
AsyncPywhatKit/src/whats.py
AsyncPywhatKit/src/Core/__init__.py
AsyncPywhatKit/src/Core/core.py
AsyncPywhatKit/src/Core/exceptions.py
AsyncPywhatKit/src/Core/log.py
AsyncPywhatKit/src/Core/data/document.png
AsyncPywhatKit/src/Core/data/img_icon.png
AsyncPywhatKit/src/Core/data/link.png
AsyncPywhatKit/src/Core/data/link2.png
AsyncPywhatKit/src/Core/data/photo_or_video.png
AsyncPywhatKit/src/Core/data/pywhatkit_smile.png
AsyncPywhatKit/src/Core/data/pywhatkit_smile1.png
AsyncPywhatKit/src/Core/data/searchbar2.png
AsyncPywhatKit/src/Core/data/unread_icon.png
AsyncPywhatKit-2.2.6.dist-info/LICENSE.md
AsyncPywhatKit-2.2.6.dist-info/METADATA
AsyncPywhatKit-2.2.6.dist-info/WHEEL
AsyncPywhatKit-2.2.6.dist-info/top_level.txt
AsyncPywhatKit-2.2.6.dist-info/RECORD
