Metadata-Version: 2.1
Name: AsyncPywhatKit
Version: 2.2.6
Summary: AsyncPywhatKit is a Simple and Powerful WhatsApp Automation Library with many useful Features
Home-page: https://github.com/SigireddyBalasai/AsyncPywhatKit
Download-URL: https://github.com/SigireddyBalasai/AsyncPywhatKit/archive/refs/tags/1.0.tar.gz
Author: SigireddyBalasai
Author-email: sigireddybalasai@gmail.com
License: MIT
Keywords: sendwhatmsg,info,playonyt,search,watch_tutorial,async pywhatkit
Classifier: Development Status :: 5 - Production/Stable
Classifier: Intended Audience :: Developers
Classifier: Topic :: Software Development :: Build Tools
Classifier: License :: OSI Approved :: MIT License
Classifier: Programming Language :: Python :: 3.8
Classifier: Programming Language :: Python :: 3.9
Classifier: Programming Language :: Python :: 3.10
Classifier: Programming Language :: Python :: 3.11
License-File: LICENSE.md
Requires-Dist: asyncio (~=3.4.3)
Requires-Dist: aiohttp (~=3.8.3)
Requires-Dist: PyAutoGUI (~=0.9.53)
Requires-Dist: wikipedia (~=1.4.0)
Requires-Dist: Pillow (~=9.4.0)
Requires-Dist: pyperclip (~=1.8.2)
Requires-Dist: keyboard (~=0.13.5)
Requires-Dist: Flask (~=2.2.2)
Requires-Dist: numpy (~=1.24.1)
Requires-Dist: opencv-python (~=4.7.0.68)
